codatsyncexpenses/__init__.py
codatsyncexpenses/companies.py
codatsyncexpenses/configuration.py
codatsyncexpenses/connections.py
codatsyncexpenses/expenses.py
codatsyncexpenses/mapping_options.py
codatsyncexpenses/sdk.py
codatsyncexpenses/sdkconfiguration.py
codatsyncexpenses/sync.py
codatsyncexpenses/sync_status.py
codatsyncexpenses/transaction_status.py
codatsyncexpenses/_hooks/__init__.py
codatsyncexpenses/_hooks/registration.py
codatsyncexpenses/_hooks/sdkhooks.py
codatsyncexpenses/_hooks/types.py
codatsyncexpenses/models/__init__.py
codatsyncexpenses/models/errors/__init__.py
codatsyncexpenses/models/errors/errormessage.py
codatsyncexpenses/models/errors/sdkerror.py
codatsyncexpenses/models/operations/__init__.py
codatsyncexpenses/models/operations/create_company.py
codatsyncexpenses/models/operations/create_connection.py
codatsyncexpenses/models/operations/create_expense_dataset.py
codatsyncexpenses/models/operations/create_partner_expense_connection.py
codatsyncexpenses/models/operations/delete_company.py
codatsyncexpenses/models/operations/delete_connection.py
codatsyncexpenses/models/operations/get_company.py
codatsyncexpenses/models/operations/get_company_configuration.py
codatsyncexpenses/models/operations/get_connection.py
codatsyncexpenses/models/operations/get_last_successful_sync.py
codatsyncexpenses/models/operations/get_latest_sync.py
codatsyncexpenses/models/operations/get_mapping_options.py
codatsyncexpenses/models/operations/get_sync_by_id.py
codatsyncexpenses/models/operations/get_sync_transaction.py
codatsyncexpenses/models/operations/initiate_sync.py
codatsyncexpenses/models/operations/list_companies.py
codatsyncexpenses/models/operations/list_connections.py
codatsyncexpenses/models/operations/list_sync_transactions.py
codatsyncexpenses/models/operations/list_syncs.py
codatsyncexpenses/models/operations/save_company_configuration.py
codatsyncexpenses/models/operations/unlink_connection.py
codatsyncexpenses/models/operations/update_company.py
codat_sync_for_expenses_version_1-0.5.0.dist-info/METADATA
codat_sync_for_expenses_version_1-0.5.0.dist-info/WHEEL
codat_sync_for_expenses_version_1-0.5.0.dist-info/top_level.txt
codat_sync_for_expenses_version_1-0.5.0.dist-info/RECORD
